MANIFEST.in
README.md
setup.cfg
setup.py
RecLab.egg-info/PKG-INFO
RecLab.egg-info/SOURCES.txt
RecLab.egg-info/dependency_links.txt
RecLab.egg-info/requires.txt
RecLab.egg-info/top_level.txt
reclab/__init__.py
reclab/data_utils.py
reclab/environments/__init__.py
reclab/environments/beta_rank.py
reclab/environments/contextual.py
reclab/environments/environment.py
reclab/environments/fixed_rating.py
reclab/environments/latent_factors.py
reclab/environments/registry.py
reclab/environments/schmit.py
reclab/environments/topics.py
reclab/recommenders/__init__.py
reclab/recommenders/baseline.py
reclab/recommenders/knn_recommender.py
reclab/recommenders/libfm.py
reclab/recommenders/recommender.py
reclab/recommenders/sparse.py
reclab/recommenders/top_pop.py
reclab/recommenders/autorec/__init__.py
reclab/recommenders/autorec/autorec.py
reclab/recommenders/cfnade/__init__.py
reclab/recommenders/cfnade/cfnade.py
reclab/recommenders/llorma/__init__.py
reclab/recommenders/llorma/llorma.py
reclab/recommenders/llorma/llorma_lib/__init__.py
reclab/recommenders/llorma/llorma_lib/anchor.py
reclab/recommenders/llorma/llorma_lib/llorma_g.py
reclab/recommenders/llorma/llorma_lib/train_utils.py
tests/__init__.py
tests/test_autorec.py
tests/test_beta_rank.py
tests/test_cfnade.py
tests/test_contextual.py
tests/test_ease.py
tests/test_fixed.py
tests/test_knn.py
tests/test_libfm.py
tests/test_llorma.py
tests/test_simple_example.py
tests/test_slim.py
tests/test_top_pop.py
tests/test_topics.py
tests/utils.py