Metadata-Version: 2.1
Name: RecLab
Version: 0.1.2
Summary: A simulation framework for recommender systems.
Home-page: https://berkeley-reclab.github.io/
Author: Karl Krauth
Author-email: karl.krauth@gmail.com
License: MIT
Download-URL: https://github.com/berkeley-reclab/RecLab/archive/v0.1.2.tar.gz
Keywords: recommender,recommendation,simulation,evaluation
Platform: UNKNOWN
Classifier: Development Status :: 3 - Alpha
Classifier: Intended Audience :: Science/Research
Classifier: Topic :: Scientific/Engineering :: Artificial Intelligence
Classifier: License :: OSI Approved :: MIT License
Classifier: Programming Language :: Python :: 3
Classifier: Programming Language :: Python :: 3.6
Classifier: Programming Language :: Python :: 3.7
Classifier: Programming Language :: Python :: 3.8
Requires-Python: >=3.6
Provides-Extra: recommenders
